WebCrawleEslite/Keywords_Page-All_eslite.py
WebCrawleEslite/ListKeywords_Page-All_eslite.py
WebCrawleEslite/Setting_Page_Keyworks_eslite.py
WebCrawleEslite/__init__.py
WebCrawleEslite/book_1.py
WebCrawleEslite-0.1.3.dist-info/LICENSE
WebCrawleEslite-0.1.3.dist-info/METADATA
WebCrawleEslite-0.1.3.dist-info/WHEEL
WebCrawleEslite-0.1.3.dist-info/top_level.txt
WebCrawleEslite-0.1.3.dist-info/RECORD
