Metadata-Version: 2.1
Name: WebCrawleEslite
Version: 0.1.3
Summary: bookstore WebCrawle Eslite
Home-page: https://github.com/u3814520/WebCrawle-eslite
Author: chiao ting
Author-email: u3814520@gmail.com
License: MIT
Platform: UNKNOWN
Classifier: License :: OSI Approved :: MIT License
Classifier: Programming Language :: Python
Classifier: Programming Language :: Python :: 3
Classifier: Programming Language :: Python :: 3.6
Classifier: Programming Language :: Python :: Implementation :: CPython
Classifier: Programming Language :: Python :: Implementation :: PyPy
Requires-Python: >=3.6.0
License-File: LICENSE
Requires-Dist: requests
Requires-Dist: pandas
Requires-Dist: fake-useragent
Requires-Dist: bs4
